[
  {
    "grade": "1",
    "section": "A",
    "user_id": "clzbjhumd000eev7me67cuf2b",
    "educational_level_id": "clzbjhsl5000cev7mbb6edisb",
    "parentId": "clzbjhuvp000pev7mxq17jprt",
    "feedback": "unde tristis terebro aeger acervus tepidus appositus adeptio cena charisma"
  },
  {
    "grade": "2",
    "section": "B",
    "user_id": "clzbjhumu000fev7msnt81it6",
    "educational_level_id": "clzbjhsl5000cev7mbb6edisb",
    "parentId": "clzbjhuvp000qev7mts5ecb8c",
    "feedback": "unus repudiandae suffoco et turpis timidus copiose vivo amplexus currus"
  },
  {
    "grade": "3",
    "section": "C",
    "user_id": "clzbjhun0000gev7musmrjxz6",
    "educational_level_id": "clzbjhsl5000cev7mbb6edisb",
    "parentId": "clzbjhuvp000rev7mylng1dm4",
    "feedback": "surculus ab carpo convoco aggredior vero numquam considero tamdiu depopulo"
  },
  {
    "grade": "4",
    "section": "D",
    "user_id": "clzbjhund000hev7m0lxm3mpk",
    "educational_level_id": "clzbjhsl5000cev7mbb6edisb",
    "parentId": "clzbjhuvp000sev7m6xv8ecxo",
    "feedback": "tremo officia illo adfectus claustrum unus sustineo laudantium color quo"
  }
]