[
  {
    "name": "Arturo Gallego",
    "password": "70zaXkob",
    "email": "0arturo.gallego@example.com",
    "state": "ACTIVE",
    "type_user": "STUDENT"
  },
  {
    "name": "Marta Ortega",
    "password": "jAm9UmwB",
    "email": "1marta.ortega@example.com",
    "state": "ACTIVE",
    "type_user": "STUDENT"
  },
  {
    "name": "Julio Esteban",
    "password": "va3CDA5t",
    "email": "2julio.esteban@example.com",
    "state": "ACTIVE",
    "type_user": "STUDENT"
  },
  {
    "name": "Remedios Ferrer",
    "password": "W14HTOri",
    "email": "3remedios.ferrer@example.com",
    "state": "ACTIVE",
    "type_user": "STUDENT"
  },
  {
    "name": "Julián Fernández",
    "password": "M52Gi75G",
    "email": "4julian.fernandez@example.com",
    "state": "ACTIVE",
    "type_user": "STUDENT"
  },
  {
    "name": "Remedios Lozano",
    "password": "fw2w41zP",
    "email": "5remedios.lozano@example.com",
    "state": "ACTIVE",
    "type_user": "STUDENT"
  },
  {
    "name": "Manuela Herrero",
    "password": "GQzl9xRh",
    "email": "6manuela.herrero@example.com",
    "state": "ACTIVE",
    "type_user": "STUDENT"
  },
  {
    "name": "Rosa Muñoz",
    "password": "Ux147Sng",
    "email": "7rosa.munoz@example.com",
    "state": "ACTIVE",
    "type_user": "STUDENT"
  },
  {
    "name": "Lourdes Cano",
    "password": "fucQqwlC",
    "email": "8lourdes.cano@example.com",
    "state": "ACTIVE",
    "type_user": "STUDENT"
  },
  {
    "name": "Alicia Cruz",
    "password": "5fN57izb",
    "email": "9alicia.cruz@example.com",
    "state": "ACTIVE",
    "type_user": "STUDENT"
  },
  {
    "name": "Rubén Flores",
    "password": "EYU8fcpd",
    "email": "10ruben.flores@example.com",
    "state": "ACTIVE",
    "type_user": "STUDENT"
  },
  {
    "name": "Francisco Gallego",
    "password": "WTFkHBTg",
    "email": "11francisco.gallego@example.com",
    "state": "ACTIVE",
    "type_user": "STUDENT"
  },
  {
    "name": "Sofia Iglesias",
    "password": "JJApqvkw",
    "email": "12sofia.iglesias@example.com",
    "state": "ACTIVE",
    "type_user": "STUDENT"
  },
  {
    "name": "Isabel García",
    "password": "tMFmYB4U",
    "email": "13isabel.garcia@example.com",
    "state": "ACTIVE",
    "type_user": "STUDENT"
  },
  {
    "name": "Inmaculada Lorenzo",
    "password": "I9glRnuh",
    "email": "14inmaculada.lorenzo@example.com",
    "state": "ACTIVE",
    "type_user": "STUDENT"
  },
  {
    "name": "Emilio Torres",
    "password": "9wQmo5rb",
    "email": "15emilio.torres@example.com",
    "state": "ACTIVE",
    "type_user": "STUDENT"
  },
  {
    "name": "Mariano Jiménez",
    "password": "ZnDPrLrT",
    "email": "16mariano.jimenez@example.com",
    "state": "ACTIVE",
    "type_user": "STUDENT"
  },
  {
    "name": "Juana Diez",
    "password": "ztrJbHP5",
    "email": "17juana.diez@example.com",
    "state": "ACTIVE",
    "type_user": "STUDENT"
  },
  {
    "name": "Eduardo Rodríguez",
    "password": "26jeb0CD",
    "email": "18eduardo.rodriguez@example.com",
    "state": "ACTIVE",
    "type_user": "STUDENT"
  },
  {
    "name": "Rafael Ramírez",
    "password": "BoYByAja",
    "email": "19rafael.ramirez@example.com",
    "state": "ACTIVE",
    "type_user": "STUDENT"
  },
  {
    "name": "Héctor Santos",
    "password": "HLaYwcXr",
    "email": "20hector.santos@example.com",
    "state": "ACTIVE",
    "type_user": "STUDENT"
  },
  {
    "name": "Esteban Esteban",
    "password": "45OEruTA",
    "email": "21esteban.esteban@example.com",
    "state": "ACTIVE",
    "type_user": "STUDENT"
  },
  {
    "name": "Héctor Martin",
    "password": "KLwdmSen",
    "email": "22hector.martin@example.com",
    "state": "ACTIVE",
    "type_user": "STUDENT"
  },
  {
    "name": "Encarnación Márquez",
    "password": "LB1Y4VTx",
    "email": "23encarnacion.marquez@example.com",
    "state": "ACTIVE",
    "type_user": "STUDENT"
  },
  {
    "name": "Nerea Suarez",
    "password": "yYjL71E4",
    "email": "24nerea.suarez@example.com",
    "state": "ACTIVE",
    "type_user": "STUDENT"
  },
  {
    "name": "Alba Gutiérrez",
    "password": "1H1CAjQF",
    "email": "25alba.gutierrez@example.com",
    "state": "ACTIVE",
    "type_user": "STUDENT"
  },
  {
    "name": "Remedios Vega",
    "password": "HGteudq9",
    "email": "26remedios.vega@example.com",
    "state": "ACTIVE",
    "type_user": "STUDENT"
  },
  {
    "name": "Blanca Herrero",
    "password": "DUYYeB7R",
    "email": "27blanca.herrero@example.com",
    "state": "ACTIVE",
    "type_user": "STUDENT"
  },
  {
    "name": "Daniel Diaz",
    "password": "bosQxHGq",
    "email": "28daniel.diaz@example.com",
    "state": "ACTIVE",
    "type_user": "STUDENT"
  },
  {
    "name": "Raúl Sanz",
    "password": "uPfHtMt3",
    "email": "29raul.sanz@example.com",
    "state": "ACTIVE",
    "type_user": "STUDENT"
  },
  {
    "name": "Angela Torres",
    "password": "BEoYbIoZ",
    "email": "30angela.torres@example.com",
    "state": "ACTIVE",
    "type_user": "STUDENT"
  },
  {
    "name": "Sara León",
    "password": "4sPJm6zd",
    "email": "31sara.leon@example.com",
    "state": "ACTIVE",
    "type_user": "STUDENT"
  },
  {
    "name": "Mariano Muñoz",
    "password": "bhiEJixO",
    "email": "32mariano.munoz@example.com",
    "state": "ACTIVE",
    "type_user": "STUDENT"
  },
  {
    "name": "Jorge Gallego",
    "password": "eazhYNYp",
    "email": "33jorge.gallego@example.com",
    "state": "ACTIVE",
    "type_user": "STUDENT"
  },
  {
    "name": "Alicia Arias",
    "password": "lcJY0lng",
    "email": "34alicia.arias@example.com",
    "state": "ACTIVE",
    "type_user": "STUDENT"
  },
  {
    "name": "Marc Ramos",
    "password": "C0sC3TsH",
    "email": "35marc.ramos@example.com",
    "state": "ACTIVE",
    "type_user": "STUDENT"
  },
  {
    "name": "Dolores Suarez",
    "password": "rldhLS6u",
    "email": "36dolores.suarez@example.com",
    "state": "ACTIVE",
    "type_user": "STUDENT"
  },
  {
    "name": "Pilar Gutiérrez",
    "password": "6HnYLMYM",
    "email": "37pilar.gutierrez@example.com",
    "state": "ACTIVE",
    "type_user": "STUDENT"
  },
  {
    "name": "Carlos Sáez",
    "password": "6kXBllIB",
    "email": "38carlos.saez@example.com",
    "state": "ACTIVE",
    "type_user": "STUDENT"
  },
  {
    "name": "Mercedes Reyes",
    "password": "iCmMncXW",
    "email": "39mercedes.reyes@example.com",
    "state": "ACTIVE",
    "type_user": "STUDENT"
  },
  {
    "name": "Carolina Ortiz",
    "password": "5TbWUtKR",
    "email": "40carolina.ortiz@example.com",
    "state": "ACTIVE",
    "type_user": "STUDENT"
  },
  {
    "name": "Consuelo Pérez",
    "password": "Q1hCQ5tL",
    "email": "41consuelo.perez@example.com",
    "state": "ACTIVE",
    "type_user": "STUDENT"
  },
  {
    "name": "Javier Navarro",
    "password": "BGoRtuq0",
    "email": "42javier.navarro@example.com",
    "state": "ACTIVE",
    "type_user": "STUDENT"
  },
  {
    "name": "Héctor Cabrera",
    "password": "2B5cF1Ss",
    "email": "43hector.cabrera@example.com",
    "state": "ACTIVE",
    "type_user": "STUDENT"
  },
  {
    "name": "Eugenio Herrero",
    "password": "W8tZ5CIl",
    "email": "44eugenio.herrero@example.com",
    "state": "ACTIVE",
    "type_user": "STUDENT"
  },
  {
    "name": "Clara Fuentes",
    "password": "JFcTAAow",
    "email": "45clara.fuentes@example.com",
    "state": "ACTIVE",
    "type_user": "STUDENT"
  },
  {
    "name": "Miguel Ruiz",
    "password": "C8fZf6k1",
    "email": "46miguel.ruiz@example.com",
    "state": "ACTIVE",
    "type_user": "STUDENT"
  },
  {
    "name": "Pablo Duran",
    "password": "OakMbdCY",
    "email": "47pablo.duran@example.com",
    "state": "ACTIVE",
    "type_user": "STUDENT"
  },
  {
    "name": "Felipe Jiménez",
    "password": "Jv3vt42r",
    "email": "48felipe.jimenez@example.com",
    "state": "ACTIVE",
    "type_user": "STUDENT"
  },
  {
    "name": "Manuel Ramírez",
    "password": "TEg02yCN",
    "email": "49manuel.ramirez@example.com",
    "state": "ACTIVE",
    "type_user": "STUDENT"
  },
  {
    "name": "Benito Calvo",
    "password": "LAhwbyY5",
    "email": "50benito.calvo@example.com",
    "state": "ACTIVE",
    "type_user": "STUDENT"
  },
  {
    "name": "Gonzalo Domínguez",
    "password": "r5afUPaD",
    "email": "51gonzalo.dominguez@example.com",
    "state": "ACTIVE",
    "type_user": "STUDENT"
  },
  {
    "name": "Joaquin Lorenzo",
    "password": "vbN35cNu",
    "email": "52joaquin.lorenzo@example.com",
    "state": "ACTIVE",
    "type_user": "STUDENT"
  },
  {
    "name": "Julián Ferrer",
    "password": "AvCgNpjw",
    "email": "53julian.ferrer@example.com",
    "state": "ACTIVE",
    "type_user": "STUDENT"
  },
  {
    "name": "Ernesto Diaz",
    "password": "tM8QKMPj",
    "email": "54ernesto.diaz@example.com",
    "state": "ACTIVE",
    "type_user": "STUDENT"
  },
  {
    "name": "Lidia Bravo",
    "password": "dHHWnZwI",
    "email": "55lidia.bravo@example.com",
    "state": "ACTIVE",
    "type_user": "STUDENT"
  },
  {
    "name": "Sofia Ramos",
    "password": "bIkR97Tl",
    "email": "56sofia.ramos@example.com",
    "state": "ACTIVE",
    "type_user": "STUDENT"
  },
  {
    "name": "Carmen González",
    "password": "lbaXNhv9",
    "email": "57carmen.gonzalez@example.com",
    "state": "ACTIVE",
    "type_user": "STUDENT"
  },
  {
    "name": "Salvador Pascual",
    "password": "3JcxxBuC",
    "email": "58salvador.pascual@example.com",
    "state": "ACTIVE",
    "type_user": "STUDENT"
  },
  {
    "name": "Pilar Duran",
    "password": "ZhxqO9IE",
    "email": "59pilar.duran@example.com",
    "state": "ACTIVE",
    "type_user": "STUDENT"
  },
  {
    "name": "Jordi Benítez",
    "password": "M7H8bhEk",
    "email": "60jordi.benitez@example.com",
    "state": "ACTIVE",
    "type_user": "STUDENT"
  },
  {
    "name": "Ana Álvarez",
    "password": "ehO2e9Ch",
    "email": "61ana.alvarez@example.com",
    "state": "ACTIVE",
    "type_user": "STUDENT"
  },
  {
    "name": "Joaquin Navarro",
    "password": "TjOcNBCk",
    "email": "62joaquin.navarro@example.com",
    "state": "ACTIVE",
    "type_user": "STUDENT"
  },
  {
    "name": "Cristóbal Román",
    "password": "ZOJSTUeS",
    "email": "63cristobal.roman@example.com",
    "state": "ACTIVE",
    "type_user": "STUDENT"
  },
  {
    "name": "Andrea Vargas",
    "password": "qfcuk9Yu",
    "email": "64andrea.vargas@example.com",
    "state": "ACTIVE",
    "type_user": "STUDENT"
  },
  {
    "name": "Sara Reyes",
    "password": "ndSt34Hq",
    "email": "65sara.reyes@example.com",
    "state": "ACTIVE",
    "type_user": "STUDENT"
  },
  {
    "name": "Susana González",
    "password": "XdQrnCr8",
    "email": "66susana.gonzalez@example.com",
    "state": "ACTIVE",
    "type_user": "STUDENT"
  },
  {
    "name": "Alicia Rubio",
    "password": "yGWOgFYR",
    "email": "67alicia.rubio@example.com",
    "state": "ACTIVE",
    "type_user": "STUDENT"
  },
  {
    "name": "Josefina Vázquez",
    "password": "DwIDmEkU",
    "email": "68josefina.vazquez@example.com",
    "state": "ACTIVE",
    "type_user": "STUDENT"
  },
  {
    "name": "José Campos",
    "password": "QsrAFdp4",
    "email": "69jose.campos@example.com",
    "state": "ACTIVE",
    "type_user": "STUDENT"
  },
  {
    "name": "Marco Duran",
    "password": "RTaEEtw8",
    "email": "70marco.duran@example.com",
    "state": "ACTIVE",
    "type_user": "STUDENT"
  },
  {
    "name": "Alfonso Jiménez",
    "password": "cIqtdJuE",
    "email": "71alfonso.jimenez@example.com",
    "state": "ACTIVE",
    "type_user": "STUDENT"
  },
  {
    "name": "Aitor Serrano",
    "password": "bzReNhSa",
    "email": "72aitor.serrano@example.com",
    "state": "ACTIVE",
    "type_user": "STUDENT"
  },
  {
    "name": "Martín Alonso",
    "password": "uotCA42K",
    "email": "73martin.alonso@example.com",
    "state": "ACTIVE",
    "type_user": "STUDENT"
  },
  {
    "name": "Carmelo López",
    "password": "756IrsWc",
    "email": "74carmelo.lopez@example.com",
    "state": "ACTIVE",
    "type_user": "STUDENT"
  },
  {
    "name": "Adolfo Bravo",
    "password": "Ia1spl9y",
    "email": "75adolfo.bravo@example.com",
    "state": "ACTIVE",
    "type_user": "STUDENT"
  },
  {
    "name": "Lorenzo Castillo",
    "password": "McIU8IcI",
    "email": "76lorenzo.castillo@example.com",
    "state": "ACTIVE",
    "type_user": "STUDENT"
  },
  {
    "name": "Alfonso Herrera",
    "password": "Q6wA163l",
    "email": "77alfonso.herrera@example.com",
    "state": "ACTIVE",
    "type_user": "STUDENT"
  },
  {
    "name": "Alejandro Pastor",
    "password": "bGyuMrni",
    "email": "78alejandro.pastor@example.com",
    "state": "ACTIVE",
    "type_user": "STUDENT"
  },
  {
    "name": "Alexander Fernández",
    "password": "pTJEqh9V",
    "email": "79alexander.fernandez@example.com",
    "state": "ACTIVE",
    "type_user": "STUDENT"
  },
  {
    "name": "Andrea Serrano",
    "password": "rUoZSeKA",
    "email": "80andrea.serrano@example.com",
    "state": "ACTIVE",
    "type_user": "STUDENT"
  },
  {
    "name": "Beatriz Fuentes",
    "password": "zfzzTyTT",
    "email": "81beatriz.fuentes@example.com",
    "state": "ACTIVE",
    "type_user": "STUDENT"
  },
  {
    "name": "Isaac Herrero",
    "password": "t9MvmRwq",
    "email": "82isaac.herrero@example.com",
    "state": "ACTIVE",
    "type_user": "STUDENT"
  },
  {
    "name": "Tomas Márquez",
    "password": "TBtzLKKx",
    "email": "83tomas.marquez@example.com",
    "state": "ACTIVE",
    "type_user": "STUDENT"
  },
  {
    "name": "Raquel Aguilar",
    "password": "T0LLtU4V",
    "email": "84raquel.aguilar@example.com",
    "state": "ACTIVE",
    "type_user": "STUDENT"
  },
  {
    "name": "Christian Diez",
    "password": "kSjGNAOp",
    "email": "85christian.diez@example.com",
    "state": "ACTIVE",
    "type_user": "STUDENT"
  },
  {
    "name": "Oscar Márquez",
    "password": "RMFt6mG5",
    "email": "86oscar.marquez@example.com",
    "state": "ACTIVE",
    "type_user": "STUDENT"
  },
  {
    "name": "Francisco Peña",
    "password": "y4eFal3b",
    "email": "87francisco.pena@example.com",
    "state": "ACTIVE",
    "type_user": "STUDENT"
  },
  {
    "name": "Josep Martin",
    "password": "oXAyGFe0",
    "email": "88josep.martin@example.com",
    "state": "ACTIVE",
    "type_user": "STUDENT"
  },
  {
    "name": "Daniel Soler",
    "password": "iF71bs7Y",
    "email": "89daniel.soler@example.com",
    "state": "ACTIVE",
    "type_user": "STUDENT"
  },
  {
    "name": "Mercedes Garrido",
    "password": "95HBBOV9",
    "email": "90mercedes.garrido@example.com",
    "state": "ACTIVE",
    "type_user": "STUDENT"
  },
  {
    "name": "Clara Montero",
    "password": "5MyzfZkO",
    "email": "91clara.montero@example.com",
    "state": "ACTIVE",
    "type_user": "STUDENT"
  },
  {
    "name": "Alfredo Diez",
    "password": "cWvlVVBF",
    "email": "92alfredo.diez@example.com",
    "state": "ACTIVE",
    "type_user": "STUDENT"
  },
  {
    "name": "Nuria Ruiz",
    "password": "CS1qo1WQ",
    "email": "93nuria.ruiz@example.com",
    "state": "ACTIVE",
    "type_user": "STUDENT"
  },
  {
    "name": "Victoria Ibáñez",
    "password": "coT9dtM8",
    "email": "94victoria.ibanez@example.com",
    "state": "ACTIVE",
    "type_user": "STUDENT"
  },
  {
    "name": "Laura Carmona",
    "password": "ejJ96cUs",
    "email": "95laura.carmona@example.com",
    "state": "ACTIVE",
    "type_user": "STUDENT"
  },
  {
    "name": "Susana Molina",
    "password": "Mka1Q4F7",
    "email": "96susana.molina@example.com",
    "state": "ACTIVE",
    "type_user": "STUDENT"
  },
  {
    "name": "Alfonso Ferrer",
    "password": "TckR9zxV",
    "email": "97alfonso.ferrer@example.com",
    "state": "ACTIVE",
    "type_user": "STUDENT"
  },
  {
    "name": "Consuelo Iglesias",
    "password": "RqLeTRXb",
    "email": "98consuelo.iglesias@example.com",
    "state": "ACTIVE",
    "type_user": "STUDENT"
  },
  {
    "name": "Isaac Morales",
    "password": "yRMou5Kr",
    "email": "99isaac.morales@example.com",
    "state": "ACTIVE",
    "type_user": "STUDENT"
  },
  {
    "name": "Julia Muñoz",
    "password": "khiVhIB3",
    "email": "100julia.munoz@example.com",
    "state": "ACTIVE",
    "type_user": "STUDENT"
  },
  {
    "name": "Isabel Blanco",
    "password": "SjqvM0PV",
    "email": "101isabel.blanco@example.com",
    "state": "ACTIVE",
    "type_user": "STUDENT"
  },
  {
    "name": "Marc Diaz",
    "password": "K5WXbvoH",
    "email": "102marc.diaz@example.com",
    "state": "ACTIVE",
    "type_user": "STUDENT"
  },
  {
    "name": "Montserrat Ruiz",
    "password": "DjSPRrOn",
    "email": "103montserrat.ruiz@example.com",
    "state": "ACTIVE",
    "type_user": "STUDENT"
  },
  {
    "name": "Josefa Suarez",
    "password": "A3fTXaWv",
    "email": "104josefa.suarez@example.com",
    "state": "ACTIVE",
    "type_user": "STUDENT"
  },
  {
    "name": "Gustavo Moya",
    "password": "ZMPZuxqG",
    "email": "105gustavo.moya@example.com",
    "state": "ACTIVE",
    "type_user": "STUDENT"
  },
  {
    "name": "John García",
    "password": "rlyumK9q",
    "email": "106john.garcia@example.com",
    "state": "ACTIVE",
    "type_user": "STUDENT"
  },
  {
    "name": "Alba Romero",
    "password": "b8U13odf",
    "email": "107alba.romero@example.com",
    "state": "ACTIVE",
    "type_user": "STUDENT"
  },
  {
    "name": "Soledad Cortes",
    "password": "t5Sqg8RU",
    "email": "108soledad.cortes@example.com",
    "state": "ACTIVE",
    "type_user": "STUDENT"
  },
  {
    "name": "Sandra Giménez",
    "password": "wrBgpkb2",
    "email": "109sandra.gimenez@example.com",
    "state": "ACTIVE",
    "type_user": "STUDENT"
  },
  {
    "name": "Daniel Castillo",
    "password": "FtaZamD9",
    "email": "110daniel.castillo@example.com",
    "state": "ACTIVE",
    "type_user": "STUDENT"
  },
  {
    "name": "Manuel Lozano",
    "password": "GdoJDpF0",
    "email": "111manuel.lozano@example.com",
    "state": "ACTIVE",
    "type_user": "STUDENT"
  },
  {
    "name": "Alicia Iglesias",
    "password": "K4lqMl3E",
    "email": "112alicia.iglesias@example.com",
    "state": "ACTIVE",
    "type_user": "STUDENT"
  },
  {
    "name": "Olga Lozano",
    "password": "GL5HbJlp",
    "email": "113olga.lozano@example.com",
    "state": "ACTIVE",
    "type_user": "STUDENT"
  },
  {
    "name": "Amparo Rubio",
    "password": "3o83ch7I",
    "email": "114amparo.rubio@example.com",
    "state": "ACTIVE",
    "type_user": "STUDENT"
  },
  {
    "name": "Inés Rojas",
    "password": "RdelQOdk",
    "email": "115ines.rojas@example.com",
    "state": "ACTIVE",
    "type_user": "STUDENT"
  },
  {
    "name": "Adolfo Marín",
    "password": "XbgdyPoP",
    "email": "116adolfo.marin@example.com",
    "state": "ACTIVE",
    "type_user": "STUDENT"
  },
  {
    "name": "Alicia Castro",
    "password": "XlLrTPD1",
    "email": "117alicia.castro@example.com",
    "state": "ACTIVE",
    "type_user": "STUDENT"
  },
  {
    "name": "Rodrigo Nieto",
    "password": "NCDGHW34",
    "email": "118rodrigo.nieto@example.com",
    "state": "ACTIVE",
    "type_user": "STUDENT"
  },
  {
    "name": "Eva Ruiz",
    "password": "uCXWnHrv",
    "email": "119eva.ruiz@example.com",
    "state": "ACTIVE",
    "type_user": "STUDENT"
  },
  {
    "name": "Alfredo Torres",
    "password": "jfP1A3vX",
    "email": "120alfredo.torres@example.com",
    "state": "ACTIVE",
    "type_user": "PARENTS"
  },
  {
    "name": "Victoria Pascual",
    "password": "7SNnTlGF",
    "email": "121victoria.pascual@example.com",
    "state": "ACTIVE",
    "type_user": "PARENTS"
  },
  {
    "name": "Susana Vázquez",
    "password": "4f1A0UXA",
    "email": "122susana.vazquez@example.com",
    "state": "ACTIVE",
    "type_user": "PARENTS"
  },
  {
    "name": "Purificación Vicente",
    "password": "2TctH5Zt",
    "email": "123purificacion.vicente@example.com",
    "state": "ACTIVE",
    "type_user": "PARENTS"
  },
  {
    "name": "Esperanza Aguilar",
    "password": "hTIXFLQz",
    "email": "124esperanza.aguilar@example.com",
    "state": "ACTIVE",
    "type_user": "PARENTS"
  },
  {
    "name": "Valentín Muñoz",
    "password": "v0HHlPSL",
    "email": "125valentin.munoz@example.com",
    "state": "ACTIVE",
    "type_user": "PARENTS"
  },
  {
    "name": "Jonathan Cabrera",
    "password": "JLaI8ENa",
    "email": "126jonathan.cabrera@example.com",
    "state": "ACTIVE",
    "type_user": "PARENTS"
  },
  {
    "name": "Silvia Herrera",
    "password": "LddPjARo",
    "email": "127silvia.herrera@example.com",
    "state": "ACTIVE",
    "type_user": "PARENTS"
  },
  {
    "name": "Daniela Prieto",
    "password": "bxzKMPJ5",
    "email": "128daniela.prieto@example.com",
    "state": "ACTIVE",
    "type_user": "PARENTS"
  },
  {
    "name": "Sonia Núñez",
    "password": "BRgAjlWX",
    "email": "129sonia.nunez@example.com",
    "state": "ACTIVE",
    "type_user": "PARENTS"
  },
  {
    "name": "Marcos Pascual",
    "password": "7h8YMu5F",
    "email": "130marcos.pascual@example.com",
    "state": "ACTIVE",
    "type_user": "PARENTS"
  },
  {
    "name": "Samuel Garrido",
    "password": "L1SoELDT",
    "email": "131samuel.garrido@example.com",
    "state": "ACTIVE",
    "type_user": "PARENTS"
  },
  {
    "name": "Héctor Navarro",
    "password": "gaFXzWXj",
    "email": "132hector.navarro@example.com",
    "state": "ACTIVE",
    "type_user": "PARENTS"
  },
  {
    "name": "José Santiago",
    "password": "kiESE8KY",
    "email": "133jose.santiago@example.com",
    "state": "ACTIVE",
    "type_user": "PARENTS"
  },
  {
    "name": "Emilia Herrera",
    "password": "0XtBQ0it",
    "email": "134emilia.herrera@example.com",
    "state": "ACTIVE",
    "type_user": "PARENTS"
  },
  {
    "name": "Aurora Ramírez",
    "password": "MgwhY56C",
    "email": "135aurora.ramirez@example.com",
    "state": "ACTIVE",
    "type_user": "PARENTS"
  },
  {
    "name": "Mónica Fernández",
    "password": "IU6iMiM4",
    "email": "136monica.fernandez@example.com",
    "state": "ACTIVE",
    "type_user": "PARENTS"
  },
  {
    "name": "Nuria Nieto",
    "password": "DQK2NCrd",
    "email": "137nuria.nieto@example.com",
    "state": "ACTIVE",
    "type_user": "PARENTS"
  },
  {
    "name": "Ramon Álvarez",
    "password": "9TW1vfZI",
    "email": "138ramon.alvarez@example.com",
    "state": "ACTIVE",
    "type_user": "PARENTS"
  },
  {
    "name": "Marc Pascual",
    "password": "Z7lVDcq2",
    "email": "139marc.pascual@example.com",
    "state": "ACTIVE",
    "type_user": "PARENTS"
  },
  {
    "name": "Olga Vargas",
    "password": "4dKCzy0O",
    "email": "140olga.vargas@example.com",
    "state": "ACTIVE",
    "type_user": "PARENTS"
  },
  {
    "name": "Catalina Rodríguez",
    "password": "XzMvtnWz",
    "email": "141catalina.rodriguez@example.com",
    "state": "ACTIVE",
    "type_user": "PARENTS"
  },
  {
    "name": "Irene Ruiz",
    "password": "y7IGgtH7",
    "email": "142irene.ruiz@example.com",
    "state": "ACTIVE",
    "type_user": "PARENTS"
  },
  {
    "name": "Esther Gallardo",
    "password": "GiPUKv0h",
    "email": "143esther.gallardo@example.com",
    "state": "ACTIVE",
    "type_user": "PARENTS"
  },
  {
    "name": "Concepción Vicente",
    "password": "WnXBRQbj",
    "email": "144concepcion.vicente@example.com",
    "state": "ACTIVE",
    "type_user": "PARENTS"
  },
  {
    "name": "Mónica Hidalgo",
    "password": "jzhbf14N",
    "email": "145monica.hidalgo@example.com",
    "state": "ACTIVE",
    "type_user": "PARENTS"
  },
  {
    "name": "Domingo Montero",
    "password": "YJDBVtRA",
    "email": "146domingo.montero@example.com",
    "state": "ACTIVE",
    "type_user": "PARENTS"
  },
  {
    "name": "Marta Ramírez",
    "password": "I0UgntzP",
    "email": "147marta.ramirez@example.com",
    "state": "ACTIVE",
    "type_user": "PARENTS"
  },
  {
    "name": "Julia Gómez",
    "password": "QXfsMy7Q",
    "email": "148julia.gomez@example.com",
    "state": "ACTIVE",
    "type_user": "PARENTS"
  },
  {
    "name": "Daniel Ruiz",
    "password": "HYMzCmlJ",
    "email": "149daniel.ruiz@example.com",
    "state": "ACTIVE",
    "type_user": "PARENTS"
  },
  {
    "name": "Jesús Ramos",
    "password": "7TH91O85",
    "email": "150jesus.ramos@example.com",
    "state": "ACTIVE",
    "type_user": "PARENTS"
  },
  {
    "name": "Manuel Sáez",
    "password": "Mf5BJv5M",
    "email": "151manuel.saez@example.com",
    "state": "ACTIVE",
    "type_user": "PARENTS"
  },
  {
    "name": "Inmaculada Aguilar",
    "password": "u26z5yPh",
    "email": "152inmaculada.aguilar@example.com",
    "state": "ACTIVE",
    "type_user": "PARENTS"
  },
  {
    "name": "Valentín Herrero",
    "password": "0dmUVF4C",
    "email": "153valentin.herrero@example.com",
    "state": "ACTIVE",
    "type_user": "PARENTS"
  },
  {
    "name": "Teresa Ortiz",
    "password": "IlHHZIkw",
    "email": "154teresa.ortiz@example.com",
    "state": "ACTIVE",
    "type_user": "PARENTS"
  },
  {
    "name": "Xavier Vega",
    "password": "Sbs8Hsd1",
    "email": "155xavier.vega@example.com",
    "state": "ACTIVE",
    "type_user": "PARENTS"
  },
  {
    "name": "Raúl Lorenzo",
    "password": "J2u60BOo",
    "email": "156raul.lorenzo@example.com",
    "state": "ACTIVE",
    "type_user": "PARENTS"
  },
  {
    "name": "Alicia Pascual",
    "password": "KMcTKZoV",
    "email": "157alicia.pascual@example.com",
    "state": "ACTIVE",
    "type_user": "PARENTS"
  },
  {
    "name": "Yolanda Ibáñez",
    "password": "t4lze2o2",
    "email": "158yolanda.ibanez@example.com",
    "state": "ACTIVE",
    "type_user": "PARENTS"
  },
  {
    "name": "Nicolas Flores",
    "password": "omtvWjrC",
    "email": "159nicolas.flores@example.com",
    "state": "ACTIVE",
    "type_user": "PARENTS"
  },
  {
    "name": "Pilar Vázquez",
    "password": "MFa1JKAy",
    "email": "160pilar.vazquez@example.com",
    "state": "ACTIVE",
    "type_user": "PARENTS"
  },
  {
    "name": "Miriam Moreno",
    "password": "2aASg5vR",
    "email": "161miriam.moreno@example.com",
    "state": "ACTIVE",
    "type_user": "PARENTS"
  },
  {
    "name": "Gerardo Serrano",
    "password": "W6cPedw5",
    "email": "162gerardo.serrano@example.com",
    "state": "ACTIVE",
    "type_user": "PARENTS"
  },
  {
    "name": "Aurora Torres",
    "password": "ASNdKrD6",
    "email": "163aurora.torres@example.com",
    "state": "ACTIVE",
    "type_user": "PARENTS"
  },
  {
    "name": "Christian López",
    "password": "9z6il6Sp",
    "email": "164christian.lopez@example.com",
    "state": "ACTIVE",
    "type_user": "PARENTS"
  },
  {
    "name": "Javier Cano",
    "password": "qntZeCX7",
    "email": "165javier.cano@example.com",
    "state": "ACTIVE",
    "type_user": "PARENTS"
  },
  {
    "name": "Roberto Guerrero",
    "password": "mrOdcdbc",
    "email": "166roberto.guerrero@example.com",
    "state": "ACTIVE",
    "type_user": "PARENTS"
  },
  {
    "name": "Felipe Santiago",
    "password": "eCsdMbgs",
    "email": "167felipe.santiago@example.com",
    "state": "ACTIVE",
    "type_user": "PARENTS"
  },
  {
    "name": "Alicia Gil",
    "password": "ZaLPDUXY",
    "email": "168alicia.gil@example.com",
    "state": "ACTIVE",
    "type_user": "PARENTS"
  },
  {
    "name": "Isabel Peña",
    "password": "ZNY4Z4yN",
    "email": "169isabel.pena@example.com",
    "state": "ACTIVE",
    "type_user": "PARENTS"
  },
  {
    "name": "Eugenia Jiménez",
    "password": "xIZrrLrS",
    "email": "170eugenia.jimenez@example.com",
    "state": "ACTIVE",
    "type_user": "PARENTS"
  },
  {
    "name": "Inmaculada Diez",
    "password": "SFtFAKNr",
    "email": "171inmaculada.diez@example.com",
    "state": "ACTIVE",
    "type_user": "PARENTS"
  },
  {
    "name": "Daniel Garrido",
    "password": "3X2yXzwj",
    "email": "172daniel.garrido@example.com",
    "state": "ACTIVE",
    "type_user": "PARENTS"
  },
  {
    "name": "Mónica Lorenzo",
    "password": "Mf1sSF8q",
    "email": "173monica.lorenzo@example.com",
    "state": "ACTIVE",
    "type_user": "PARENTS"
  },
  {
    "name": "Elena Méndez",
    "password": "bEIcjjhE",
    "email": "174elena.mendez@example.com",
    "state": "ACTIVE",
    "type_user": "PARENTS"
  },
  {
    "name": "Lorena Prieto",
    "password": "KxlRrLgY",
    "email": "175lorena.prieto@example.com",
    "state": "ACTIVE",
    "type_user": "PARENTS"
  },
  {
    "name": "Rosario Martin",
    "password": "W45liP9G",
    "email": "176rosario.martin@example.com",
    "state": "ACTIVE",
    "type_user": "PARENTS"
  },
  {
    "name": "Milagros Cano",
    "password": "IU8XseTA",
    "email": "177milagros.cano@example.com",
    "state": "ACTIVE",
    "type_user": "PARENTS"
  },
  {
    "name": "Josefa Hernández",
    "password": "aNWk0r6I",
    "email": "178josefa.hernandez@example.com",
    "state": "ACTIVE",
    "type_user": "PARENTS"
  },
  {
    "name": "Javier Pascual",
    "password": "hpu9h4yY",
    "email": "179javier.pascual@example.com",
    "state": "ACTIVE",
    "type_user": "PARENTS"
  },
  {
    "name": "Francisco Álvarez",
    "password": "1lli8mYt",
    "email": "180francisco.alvarez@example.com",
    "state": "ACTIVE",
    "type_user": "PARENTS"
  },
  {
    "name": "Jordi Núñez",
    "password": "yinEwJGm",
    "email": "181jordi.nunez@example.com",
    "state": "ACTIVE",
    "type_user": "PARENTS"
  },
  {
    "name": "Carlos Martínez",
    "password": "ukdKS8Hv",
    "email": "182carlos.martinez@example.com",
    "state": "ACTIVE",
    "type_user": "PARENTS"
  },
  {
    "name": "Manuel Carmona",
    "password": "YLHDs3Fu",
    "email": "183manuel.carmona@example.com",
    "state": "ACTIVE",
    "type_user": "PARENTS"
  },
  {
    "name": "Jaime Martin",
    "password": "helQpAHc",
    "email": "184jaime.martin@example.com",
    "state": "ACTIVE",
    "type_user": "PARENTS"
  },
  {
    "name": "Carolina Nieto",
    "password": "e2sqkkPU",
    "email": "185carolina.nieto@example.com",
    "state": "ACTIVE",
    "type_user": "PARENTS"
  },
  {
    "name": "Eduardo Pascual",
    "password": "MbwhHbV2",
    "email": "186eduardo.pascual@example.com",
    "state": "ACTIVE",
    "type_user": "PARENTS"
  },
  {
    "name": "Daniela Bravo",
    "password": "kEgT186l",
    "email": "187daniela.bravo@example.com",
    "state": "ACTIVE",
    "type_user": "PARENTS"
  },
  {
    "name": "Amparo Suarez",
    "password": "QsJ27dFT",
    "email": "188amparo.suarez@example.com",
    "state": "ACTIVE",
    "type_user": "PARENTS"
  },
  {
    "name": "Mohamed Cano",
    "password": "yXFa6th6",
    "email": "189mohamed.cano@example.com",
    "state": "ACTIVE",
    "type_user": "PARENTS"
  },
  {
    "name": "Víctor Sánchez",
    "password": "Uy437dtb",
    "email": "190victor.sanchez@example.com",
    "state": "ACTIVE",
    "type_user": "PARENTS"
  },
  {
    "name": "Amparo Ortega",
    "password": "wXI9qieS",
    "email": "191amparo.ortega@example.com",
    "state": "ACTIVE",
    "type_user": "PARENTS"
  },
  {
    "name": "Hugo García",
    "password": "lqTKgPX1",
    "email": "192hugo.garcia@example.com",
    "state": "ACTIVE",
    "type_user": "PARENTS"
  },
  {
    "name": "Fátima González",
    "password": "oRBMCEAo",
    "email": "193fatima.gonzalez@example.com",
    "state": "ACTIVE",
    "type_user": "PARENTS"
  },
  {
    "name": "Ricardo Diaz",
    "password": "sxeYPHJX",
    "email": "194ricardo.diaz@example.com",
    "state": "ACTIVE",
    "type_user": "PARENTS"
  },
  {
    "name": "Paula Moreno",
    "password": "zBDPPmzE",
    "email": "195paula.moreno@example.com",
    "state": "ACTIVE",
    "type_user": "PARENTS"
  },
  {
    "name": "Mar García",
    "password": "OwpJdJeS",
    "email": "196mar.garcia@example.com",
    "state": "ACTIVE",
    "type_user": "PARENTS"
  },
  {
    "name": "Sonia Romero",
    "password": "AzjkIAsI",
    "email": "197sonia.romero@example.com",
    "state": "ACTIVE",
    "type_user": "PARENTS"
  },
  {
    "name": "Luis Garrido",
    "password": "ZFrr2Xqk",
    "email": "198luis.garrido@example.com",
    "state": "ACTIVE",
    "type_user": "PARENTS"
  },
  {
    "name": "Valentín Sánchez",
    "password": "mvAW9rTB",
    "email": "199valentin.sanchez@example.com",
    "state": "ACTIVE",
    "type_user": "PARENTS"
  },
  {
    "name": "José Pascual",
    "password": "UvK9MZoy",
    "email": "200jose.pascual@example.com",
    "state": "ACTIVE",
    "type_user": "PARENTS"
  },
  {
    "name": "Julio Núñez",
    "password": "zsCcKjLi",
    "email": "201julio.nunez@example.com",
    "state": "ACTIVE",
    "type_user": "PARENTS"
  },
  {
    "name": "Valentín Jiménez",
    "password": "PhpvAUV9",
    "email": "202valentin.jimenez@example.com",
    "state": "ACTIVE",
    "type_user": "PARENTS"
  },
  {
    "name": "Guillermo Pérez",
    "password": "JSH87bYe",
    "email": "203guillermo.perez@example.com",
    "state": "ACTIVE",
    "type_user": "PARENTS"
  },
  {
    "name": "Nerea Castillo",
    "password": "1YQ9nB5P",
    "email": "204nerea.castillo@example.com",
    "state": "ACTIVE",
    "type_user": "PARENTS"
  },
  {
    "name": "Ernesto Pascual",
    "password": "08RkbkZa",
    "email": "205ernesto.pascual@example.com",
    "state": "ACTIVE",
    "type_user": "PARENTS"
  },
  {
    "name": "Consuelo Sáez",
    "password": "JiJq1I0g",
    "email": "206consuelo.saez@example.com",
    "state": "ACTIVE",
    "type_user": "PARENTS"
  },
  {
    "name": "Vicente Ruiz",
    "password": "Kalk0BGU",
    "email": "207vicente.ruiz@example.com",
    "state": "ACTIVE",
    "type_user": "PARENTS"
  },
  {
    "name": "Adriana Parra",
    "password": "u1kYUOYp",
    "email": "208adriana.parra@example.com",
    "state": "ACTIVE",
    "type_user": "PARENTS"
  },
  {
    "name": "Paula Vicente",
    "password": "xtANJjo5",
    "email": "209paula.vicente@example.com",
    "state": "ACTIVE",
    "type_user": "PARENTS"
  },
  {
    "name": "Santiago González",
    "password": "DxC7umh0",
    "email": "210santiago.gonzalez@example.com",
    "state": "ACTIVE",
    "type_user": "PARENTS"
  },
  {
    "name": "Manuela Garrido",
    "password": "gQgRgR2E",
    "email": "211manuela.garrido@example.com",
    "state": "ACTIVE",
    "type_user": "PARENTS"
  },
  {
    "name": "Cristóbal Domínguez",
    "password": "E08AQnfX",
    "email": "212cristobal.dominguez@example.com",
    "state": "ACTIVE",
    "type_user": "PARENTS"
  },
  {
    "name": "Dolores Muñoz",
    "password": "HItuQEVN",
    "email": "213dolores.munoz@example.com",
    "state": "ACTIVE",
    "type_user": "PARENTS"
  },
  {
    "name": "Ismael Parra",
    "password": "SZ5LiRtT",
    "email": "214ismael.parra@example.com",
    "state": "ACTIVE",
    "type_user": "PARENTS"
  },
  {
    "name": "Carolina Hidalgo",
    "password": "PuiQuchz",
    "email": "215carolina.hidalgo@example.com",
    "state": "ACTIVE",
    "type_user": "PARENTS"
  },
  {
    "name": "Noelia Álvarez",
    "password": "wql3wPGr",
    "email": "216noelia.alvarez@example.com",
    "state": "ACTIVE",
    "type_user": "PARENTS"
  },
  {
    "name": "Valentín López",
    "password": "ph07af9s",
    "email": "217valentin.lopez@example.com",
    "state": "ACTIVE",
    "type_user": "PARENTS"
  },
  {
    "name": "Soledad Diez",
    "password": "t5rz0OCK",
    "email": "218soledad.diez@example.com",
    "state": "ACTIVE",
    "type_user": "PARENTS"
  },
  {
    "name": "Carla Bravo",
    "password": "UG5bcL5c",
    "email": "219carla.bravo@example.com",
    "state": "ACTIVE",
    "type_user": "PARENTS"
  },
  {
    "name": "Victoria Gutiérrez",
    "password": "r87SCwLp",
    "email": "220victoria.gutierrez@example.com",
    "state": "ACTIVE",
    "type_user": "PARENTS"
  },
  {
    "name": "Francisco Duran",
    "password": "GXvNYTdE",
    "email": "221francisco.duran@example.com",
    "state": "ACTIVE",
    "type_user": "PARENTS"
  },
  {
    "name": "Teresa Gómez",
    "password": "nLfgmt0K",
    "email": "222teresa.gomez@example.com",
    "state": "ACTIVE",
    "type_user": "PARENTS"
  },
  {
    "name": "Natalia Martínez",
    "password": "FtQX3lBF",
    "email": "223natalia.martinez@example.com",
    "state": "ACTIVE",
    "type_user": "PARENTS"
  },
  {
    "name": "Felipe Suarez",
    "password": "nz1XLwSS",
    "email": "224felipe.suarez@example.com",
    "state": "ACTIVE",
    "type_user": "PARENTS"
  },
  {
    "name": "German Gil",
    "password": "3NoNfFIt",
    "email": "225german.gil@example.com",
    "state": "ACTIVE",
    "type_user": "PARENTS"
  },
  {
    "name": "Carlos Jiménez",
    "password": "1bSFV5UD",
    "email": "226carlos.jimenez@example.com",
    "state": "ACTIVE",
    "type_user": "PARENTS"
  },
  {
    "name": "Noelia Duran",
    "password": "GdTlj8ER",
    "email": "227noelia.duran@example.com",
    "state": "ACTIVE",
    "type_user": "PARENTS"
  },
  {
    "name": "Laura Medina",
    "password": "UZY7OAo0",
    "email": "228laura.medina@example.com",
    "state": "ACTIVE",
    "type_user": "PARENTS"
  },
  {
    "name": "Enrique Moya",
    "password": "RfcPHAUo",
    "email": "229enrique.moya@example.com",
    "state": "ACTIVE",
    "type_user": "PARENTS"
  },
  {
    "name": "Francisca Gómez",
    "password": "ntLDmHMi",
    "email": "230francisca.gomez@example.com",
    "state": "ACTIVE",
    "type_user": "PARENTS"
  },
  {
    "name": "Angela Sáez",
    "password": "WfshDu3L",
    "email": "231angela.saez@example.com",
    "state": "ACTIVE",
    "type_user": "PARENTS"
  },
  {
    "name": "Gabriel Marín",
    "password": "VjSEddOB",
    "email": "232gabriel.marin@example.com",
    "state": "ACTIVE",
    "type_user": "PARENTS"
  },
  {
    "name": "Concepción Moya",
    "password": "duqTMfuc",
    "email": "233concepcion.moya@example.com",
    "state": "ACTIVE",
    "type_user": "PARENTS"
  },
  {
    "name": "Lourdes Bravo",
    "password": "IXAuJnfl",
    "email": "234lourdes.bravo@example.com",
    "state": "ACTIVE",
    "type_user": "PARENTS"
  },
  {
    "name": "Ana Garrido",
    "password": "DH2OQAPi",
    "email": "235ana.garrido@example.com",
    "state": "ACTIVE",
    "type_user": "PARENTS"
  },
  {
    "name": "María Gallego",
    "password": "an4P2E4A",
    "email": "236maria.gallego@example.com",
    "state": "ACTIVE",
    "type_user": "PARENTS"
  },
  {
    "name": "Anna Márquez",
    "password": "H515JZXP",
    "email": "237anna.marquez@example.com",
    "state": "ACTIVE",
    "type_user": "PARENTS"
  },
  {
    "name": "Luis Navarro",
    "password": "HjjaPHaR",
    "email": "238luis.navarro@example.com",
    "state": "ACTIVE",
    "type_user": "PARENTS"
  },
  {
    "name": "Marcos Diaz",
    "password": "37RFXdt5",
    "email": "239marcos.diaz@example.com",
    "state": "ACTIVE",
    "type_user": "PARENTS"
  },
  {
    "name": "Nicolas Cano",
    "password": "SKcv9mlH",
    "email": "240nicolas.cano@example.com",
    "state": "ACTIVE",
    "type_user": "PROFESSOR"
  },
  {
    "name": "José Muñoz",
    "password": "ORlNiilv",
    "email": "241jose.munoz@example.com",
    "state": "ACTIVE",
    "type_user": "PROFESSOR"
  },
  {
    "name": "Adolfo Gallardo",
    "password": "Nmgwm8Kd",
    "email": "242adolfo.gallardo@example.com",
    "state": "ACTIVE",
    "type_user": "PROFESSOR"
  },
  {
    "name": "Mónica Romero",
    "password": "G7Q9oMDg",
    "email": "243monica.romero@example.com",
    "state": "ACTIVE",
    "type_user": "PROFESSOR"
  },
  {
    "name": "Teresa Pérez",
    "password": "qNjwWRiO",
    "email": "244teresa.perez@example.com",
    "state": "ACTIVE",
    "type_user": "PROFESSOR"
  },
  {
    "name": "Carmelo Rodríguez",
    "password": "iyEnymYs",
    "email": "245carmelo.rodriguez@example.com",
    "state": "ACTIVE",
    "type_user": "PROFESSOR"
  },
  {
    "name": "José Ramos",
    "password": "YqvUURLh",
    "email": "246jose.ramos@example.com",
    "state": "ACTIVE",
    "type_user": "PROFESSOR"
  },
  {
    "name": "Josep Hidalgo",
    "password": "WdfVBfan",
    "email": "247josep.hidalgo@example.com",
    "state": "ACTIVE",
    "type_user": "PROFESSOR"
  },
  {
    "name": "Jaime Marín",
    "password": "Mxs8L0XZ",
    "email": "248jaime.marin@example.com",
    "state": "ACTIVE",
    "type_user": "PROFESSOR"
  },
  {
    "name": "Joan Moreno",
    "password": "ZqRXEoP2",
    "email": "249joan.moreno@example.com",
    "state": "ACTIVE",
    "type_user": "PROFESSOR"
  },
  {
    "name": "Javier Benítez",
    "password": "CMX7P6YZ",
    "email": "250javier.benitez@example.com",
    "state": "ACTIVE",
    "type_user": "PROFESSOR"
  },
  {
    "name": "Marina Ibáñez",
    "password": "wD0pRCql",
    "email": "251marina.ibanez@example.com",
    "state": "ACTIVE",
    "type_user": "PROFESSOR"
  },
  {
    "name": "Magdalena Molina",
    "password": "oDPfdaFt",
    "email": "252magdalena.molina@example.com",
    "state": "ACTIVE",
    "type_user": "PROFESSOR"
  },
  {
    "name": "Carolina Castillo",
    "password": "5GYqVafO",
    "email": "253carolina.castillo@example.com",
    "state": "ACTIVE",
    "type_user": "PROFESSOR"
  },
  {
    "name": "Adolfo Calvo",
    "password": "WfpPH13F",
    "email": "254adolfo.calvo@example.com",
    "state": "ACTIVE",
    "type_user": "PROFESSOR"
  },
  {
    "name": "Rocío Castro",
    "password": "IJWBD3E3",
    "email": "255rocio.castro@example.com",
    "state": "ACTIVE",
    "type_user": "PROFESSOR"
  },
  {
    "name": "Isabel Garrido",
    "password": "mvOIZVwr",
    "email": "256isabel.garrido@example.com",
    "state": "ACTIVE",
    "type_user": "PROFESSOR"
  },
  {
    "name": "Ernesto González",
    "password": "UC9a8Nt4",
    "email": "257ernesto.gonzalez@example.com",
    "state": "ACTIVE",
    "type_user": "PROFESSOR"
  },
  {
    "name": "Fátima Gómez",
    "password": "2P6hDNZt",
    "email": "258fatima.gomez@example.com",
    "state": "ACTIVE",
    "type_user": "PROFESSOR"
  },
  {
    "name": "Lucia Delgado",
    "password": "3fCuLhHJ",
    "email": "259lucia.delgado@example.com",
    "state": "ACTIVE",
    "type_user": "PROFESSOR"
  },
  {
    "name": "Marta Morales",
    "password": "0n2bnJl1",
    "email": "260marta.morales@example.com",
    "state": "ACTIVE",
    "type_user": "PROFESSOR"
  },
  {
    "name": "Julia Sáez",
    "password": "JXJEEt48",
    "email": "261julia.saez@example.com",
    "state": "ACTIVE",
    "type_user": "PROFESSOR"
  },
  {
    "name": "Esperanza Sáez",
    "password": "6nPYbP6Z",
    "email": "262esperanza.saez@example.com",
    "state": "ACTIVE",
    "type_user": "PROFESSOR"
  },
  {
    "name": "Asunción Alonso",
    "password": "9CexxWeB",
    "email": "263asuncion.alonso@example.com",
    "state": "ACTIVE",
    "type_user": "PROFESSOR"
  },
  {
    "name": "Eugenia Alonso",
    "password": "NnkOFa8A",
    "email": "264eugenia.alonso@example.com",
    "state": "ACTIVE",
    "type_user": "PROFESSOR"
  },
  {
    "name": "Salvador Ibáñez",
    "password": "LiiAn80P",
    "email": "265salvador.ibanez@example.com",
    "state": "ACTIVE",
    "type_user": "PROFESSOR"
  },
  {
    "name": "Laura Ibáñez",
    "password": "UFfUc99D",
    "email": "266laura.ibanez@example.com",
    "state": "ACTIVE",
    "type_user": "PROFESSOR"
  },
  {
    "name": "Remedios Diaz",
    "password": "T1XqibaV",
    "email": "267remedios.diaz@example.com",
    "state": "ACTIVE",
    "type_user": "PROFESSOR"
  },
  {
    "name": "Marcos Márquez",
    "password": "O1oPtXTw",
    "email": "268marcos.marquez@example.com",
    "state": "ACTIVE",
    "type_user": "PROFESSOR"
  },
  {
    "name": "Asunción López",
    "password": "zauqigGq",
    "email": "269asuncion.lopez@example.com",
    "state": "ACTIVE",
    "type_user": "PROFESSOR"
  },
  {
    "name": "Andrea Iglesias",
    "password": "wU9VUWkw",
    "email": "270andrea.iglesias@example.com",
    "state": "ACTIVE",
    "type_user": "PROFESSOR"
  },
  {
    "name": "Aurora Morales",
    "password": "0lIJKMkf",
    "email": "271aurora.morales@example.com",
    "state": "ACTIVE",
    "type_user": "PROFESSOR"
  },
  {
    "name": "Josefa Blanco",
    "password": "KfExAj0u",
    "email": "272josefa.blanco@example.com",
    "state": "ACTIVE",
    "type_user": "PROFESSOR"
  },
  {
    "name": "Mohamed López",
    "password": "G0WP3Vhp",
    "email": "273mohamed.lopez@example.com",
    "state": "ACTIVE",
    "type_user": "PROFESSOR"
  },
  {
    "name": "Mohamed Ortiz",
    "password": "E6ox2Mzq",
    "email": "274mohamed.ortiz@example.com",
    "state": "ACTIVE",
    "type_user": "PROFESSOR"
  },
  {
    "name": "Carla Navarro",
    "password": "VVfejFxy",
    "email": "275carla.navarro@example.com",
    "state": "ACTIVE",
    "type_user": "PROFESSOR"
  },
  {
    "name": "Joaquin Rodríguez",
    "password": "JIbWgFn2",
    "email": "276joaquin.rodriguez@example.com",
    "state": "ACTIVE",
    "type_user": "PROFESSOR"
  },
  {
    "name": "Carlos González",
    "password": "W8eenabc",
    "email": "277carlos.gonzalez@example.com",
    "state": "ACTIVE",
    "type_user": "PROFESSOR"
  },
  {
    "name": "Fernando Nieto",
    "password": "dtpYiD8q",
    "email": "278fernando.nieto@example.com",
    "state": "ACTIVE",
    "type_user": "PROFESSOR"
  },
  {
    "name": "Ramon Torres",
    "password": "uu8yIwLI",
    "email": "279ramon.torres@example.com",
    "state": "ACTIVE",
    "type_user": "PROFESSOR"
  },
  {
    "name": "Vicenta Ramírez",
    "password": "kJSk6roh",
    "email": "280vicenta.ramirez@example.com",
    "state": "ACTIVE",
    "type_user": "PROFESSOR"
  },
  {
    "name": "Andrea Ibáñez",
    "password": "T2hX5NsT",
    "email": "281andrea.ibanez@example.com",
    "state": "ACTIVE",
    "type_user": "PROFESSOR"
  },
  {
    "name": "Gema Diaz",
    "password": "CaAZs7ey",
    "email": "282gema.diaz@example.com",
    "state": "ACTIVE",
    "type_user": "PROFESSOR"
  },
  {
    "name": "Nieves Giménez",
    "password": "HfIX6Jbb",
    "email": "283nieves.gimenez@example.com",
    "state": "ACTIVE",
    "type_user": "PROFESSOR"
  },
  {
    "name": "Xavier Fernández",
    "password": "yDkr6I4d",
    "email": "284xavier.fernandez@example.com",
    "state": "ACTIVE",
    "type_user": "PROFESSOR"
  },
  {
    "name": "Gregorio Muñoz",
    "password": "dh0XlsoU",
    "email": "285gregorio.munoz@example.com",
    "state": "ACTIVE",
    "type_user": "PROFESSOR"
  },
  {
    "name": "Marco Benítez",
    "password": "RjUbI4U8",
    "email": "286marco.benitez@example.com",
    "state": "ACTIVE",
    "type_user": "PROFESSOR"
  },
  {
    "name": "Ernesto Vargas",
    "password": "ngNua2YU",
    "email": "287ernesto.vargas@example.com",
    "state": "ACTIVE",
    "type_user": "PROFESSOR"
  },
  {
    "name": "Soledad Montero",
    "password": "UQuk5wVS",
    "email": "288soledad.montero@example.com",
    "state": "ACTIVE",
    "type_user": "PROFESSOR"
  },
  {
    "name": "Iker Ferrer",
    "password": "f38cqmwn",
    "email": "289iker.ferrer@example.com",
    "state": "ACTIVE",
    "type_user": "PROFESSOR"
  },
  {
    "name": "Julia Vargas",
    "password": "6BU2Rrjp",
    "email": "290julia.vargas@example.com",
    "state": "ACTIVE",
    "type_user": "PROFESSOR"
  },
  {
    "name": "Rosa Reyes",
    "password": "3rPW32lj",
    "email": "291rosa.reyes@example.com",
    "state": "ACTIVE",
    "type_user": "PROFESSOR"
  },
  {
    "name": "Francisco Román",
    "password": "unY7OWL7",
    "email": "292francisco.roman@example.com",
    "state": "ACTIVE",
    "type_user": "PROFESSOR"
  },
  {
    "name": "Trinidad Torres",
    "password": "ZFpkEXXk",
    "email": "293trinidad.torres@example.com",
    "state": "ACTIVE",
    "type_user": "PROFESSOR"
  },
  {
    "name": "Emilia Moya",
    "password": "0JzePERe",
    "email": "294emilia.moya@example.com",
    "state": "ACTIVE",
    "type_user": "PROFESSOR"
  },
  {
    "name": "Antonia Santiago",
    "password": "hXtNNGmr",
    "email": "295antonia.santiago@example.com",
    "state": "ACTIVE",
    "type_user": "PROFESSOR"
  },
  {
    "name": "Joaquin Méndez",
    "password": "Hn8Uy2CI",
    "email": "296joaquin.mendez@example.com",
    "state": "ACTIVE",
    "type_user": "PROFESSOR"
  },
  {
    "name": "José Mora",
    "password": "AvRqdAXX",
    "email": "297jose.mora@example.com",
    "state": "ACTIVE",
    "type_user": "PROFESSOR"
  },
  {
    "name": "Joaquin Vicente",
    "password": "cL1xkyE8",
    "email": "298joaquin.vicente@example.com",
    "state": "ACTIVE",
    "type_user": "PROFESSOR"
  },
  {
    "name": "Sonia Morales",
    "password": "fjURMxn1",
    "email": "299sonia.morales@example.com",
    "state": "ACTIVE",
    "type_user": "PROFESSOR"
  }
]
